{
  "resolvedId": "C:/Users/kchar/OneDrive/Documents/Projects/limelightsmp-website/app.vue?vue&type=style&index=0&scoped=8b8048b7&lang.scss?inline&used",
  "transforms": [
    {
      "name": "vite:vue",
      "result": "\r\n.v-card.on-hover.v-theme--dark {\r\n  background-color: rgba(#FFF, 0.8),\r\n\r\n}\r\n\r\n.v-card__text {\r\n  color: #000\r\n}\r\n",
      "start": 1707368388300,
      "end": 1707368388301
    },
    {
      "name": "nuxt:layer-aliasing",
      "start": 1707368388301,
      "end": 1707368388301,
      "order": "pre"
    },
    {
      "name": "nuxt:layer-aliasing",
      "start": 1707368388301,
      "end": 1707368388301,
      "order": "pre"
    },
    {
      "name": "nuxt:server-devonly:transform",
      "start": 1707368388301,
      "end": 1707368388301,
      "order": "pre"
    },
    {
      "name": "nuxt:server-devonly:transform",
      "start": 1707368388301,
      "end": 1707368388301,
      "order": "pre"
    },
    {
      "name": "nuxt:client-fallback-auto-id",
      "start": 1707368388301,
      "end": 1707368388301,
      "order": "pre"
    },
    {
      "name": "vite:css",
      "result": ".v-card.on-hover.v-theme--dark{background-color:hsla(0,0%,100%,.8)}.v-card__text{color:#000}",
      "start": 1707368388301,
      "end": 1707368388325,
      "order": "normal",
      "sourcemaps": {
        "version": 3,
        "file": "C:/Users/kchar/OneDrive/Documents/Projects/limelightsmp-website/app.vue",
        "mappings": "AACA,+BACE,oCAIF,cACE",
        "names": [],
        "sources": [
          "C:/Users/kchar/OneDrive/Documents/Projects/limelightsmp-website/app.vue"
        ],
        "sourcesContent": [
          null
        ]
      }
    },
    {
      "name": "vite:esbuild",
      "start": 1707368388325,
      "end": 1707368388325,
      "order": "normal"
    },
    {
      "name": "vite:json",
      "start": 1707368388325,
      "end": 1707368388325,
      "order": "normal"
    },
    {
      "name": "vite:worker",
      "start": 1707368388325,
      "end": 1707368388325,
      "order": "normal"
    },
    {
      "name": "vite:vue",
      "result": ".v-card.on-hover.v-theme--dark[data-v-8b8048b7]{background-color:hsla(0,0%,100%,.8)}.v-card__text[data-v-8b8048b7]{color:#000}",
      "start": 1707368388325,
      "end": 1707368388327,
      "order": "normal",
      "sourcemaps": {
        "file": "C:/Users/kchar/OneDrive/Documents/Projects/limelightsmp-website/app.vue",
        "mappings": "AAAA,gDAA+B,mCAAmC,CAAC,+BAAc,UAAU",
        "names": [],
        "sources": [
          "C:/Users/kchar/OneDrive/Documents/Projects/limelightsmp-website/app.vue"
        ],
        "sourcesContent": [
          null
        ],
        "version": 3
      }
    },
    {
      "name": "vite:vue-jsx",
      "start": 1707368388327,
      "end": 1707368388327,
      "order": "normal"
    },
    {
      "name": "replace",
      "start": 1707368388327,
      "end": 1707368388327,
      "order": "normal"
    },
    {
      "name": "replace",
      "start": 1707368388327,
      "end": 1707368388327,
      "order": "normal"
    },
    {
      "name": "nuxt:remove-plugin-metadata",
      "start": 1707368388327,
      "end": 1707368388327,
      "order": "normal"
    },
    {
      "name": "nuxt:remove-plugin-metadata",
      "start": 1707368388327,
      "end": 1707368388327,
      "order": "normal"
    },
    {
      "name": "nuxt:components:imports",
      "start": 1707368388327,
      "end": 1707368388327,
      "order": "normal"
    },
    {
      "name": "replace",
      "start": 1707368388327,
      "end": 1707368388327,
      "order": "normal"
    },
    {
      "name": "ssr-styles",
      "start": 1707368388327,
      "end": 1707368388327,
      "order": "normal"
    },
    {
      "name": "vite:define",
      "start": 1707368388327,
      "end": 1707368388327,
      "order": "normal"
    },
    {
      "name": "vite:css-post",
      "result": "export default \".v-card.on-hover.v-theme--dark[data-v-8b8048b7]{background-color:hsla(0,0%,100%,.8)}.v-card__text[data-v-8b8048b7]{color:#000}\"",
      "start": 1707368388327,
      "end": 1707368388327,
      "order": "normal",
      "sourcemaps": {
        "mappings": ""
      }
    },
    {
      "name": "vite:build-html",
      "start": 1707368388327,
      "end": 1707368388327,
      "order": "normal"
    },
    {
      "name": "vite:worker-import-meta-url",
      "start": 1707368388327,
      "end": 1707368388327,
      "order": "normal"
    },
    {
      "name": "vite:asset-import-meta-url",
      "start": 1707368388327,
      "end": 1707368388327,
      "order": "normal"
    },
    {
      "name": "commonjs",
      "start": 1707368388327,
      "end": 1707368388327,
      "order": "normal"
    },
    {
      "name": "vite:dynamic-import-vars",
      "start": 1707368388327,
      "end": 1707368388327,
      "order": "normal"
    },
    {
      "name": "vite:import-glob",
      "start": 1707368388327,
      "end": 1707368388327,
      "order": "normal"
    },
    {
      "name": "nuxt:composable-keys",
      "start": 1707368388327,
      "end": 1707368388327,
      "order": "post"
    },
    {
      "name": "nuxt:composable-keys",
      "start": 1707368388327,
      "end": 1707368388327,
      "order": "post"
    },
    {
      "name": "nuxt:imports-transform",
      "start": 1707368388327,
      "end": 1707368388327,
      "order": "post"
    },
    {
      "name": "nuxt:imports-transform",
      "start": 1707368388327,
      "end": 1707368388327,
      "order": "post"
    },
    {
      "name": "unctx:transform",
      "start": 1707368388327,
      "end": 1707368388327,
      "order": "post"
    },
    {
      "name": "unctx:transform",
      "start": 1707368388327,
      "end": 1707368388327,
      "order": "post"
    },
    {
      "name": "nuxt:tree-shake-template",
      "start": 1707368388327,
      "end": 1707368388328,
      "order": "post"
    },
    {
      "name": "nuxt:components-loader",
      "start": 1707368388328,
      "end": 1707368388328,
      "order": "post"
    },
    {
      "name": "nuxt:tree-shake-composables:transform",
      "start": 1707368388328,
      "end": 1707368388328,
      "order": "post"
    },
    {
      "name": "vite:build-import-analysis",
      "start": 1707368388328,
      "end": 1707368388328,
      "order": "normal"
    },
    {
      "name": "vite:reporter",
      "start": 1707368388328,
      "end": 1707368388328,
      "order": "normal"
    }
  ]
}
